<?xml version="1.0" encoding="UTF-8" standalone="yes"?>
<persistence xmlns="http://xmlns.jcp.org/xml/ns/persistence"
             xmlns:xsi="http://www.w3.org/2001/XMLSchema-instance"
             xsi:schemaLocation="http://xmlns.jcp.org/xml/ns/persistence http://xmlns.jcp.org/xml/ns/persistence/persistence_2_2.xsd"
             version="2.2">
    <persistence-unit name="default">
        <provider>org.hibernate.jpa.HibernatePersistenceProvider</provider>
        <class>umb.cliente.clienteumb.model.dao.ClientDAO</class>
        <class>umb.cliente.clienteumb.model.dao.TypeIdDAO</class>
        <class>umb.cliente.clienteumb.model.dao.UserDAO</class>
        <class>umb.cliente.clienteumb.model.dao.CommercialAreaDAO</class>
        <class>umb.cliente.clienteumb.model.dao.EmployeeDAO</class>
        <properties>
            <property name="hibernate.dialect" value="org.hibernate.dialect.MySQL5Dialect"/>
            <property name="hibernate.hbm2ddl.auto" value="create-drop"/>
            <property name="javax.persistence.jdbc.url" value="jdbc:mysql://localhost:3306/clientUMB?createDatabaseIfNotExist=true"/>
            <property name="javax.persistence.jdbc.user" value="umb"/>
            <property name="javax.persistence.jdbc.driver" value="com.mysql.jdbc.Driver"/>
            <property name="javax.persistence.jdbc.password" value="clientUMB"/>
        </properties>
    </persistence-unit>
</persistence>

